subsetter.py
rdbms_subsetter-0.2.6.dist-info/DESCRIPTION.rst
rdbms_subsetter-0.2.6.dist-info/METADATA
rdbms_subsetter-0.2.6.dist-info/RECORD
rdbms_subsetter-0.2.6.dist-info/WHEEL
rdbms_subsetter-0.2.6.dist-info/entry_points.txt
rdbms_subsetter-0.2.6.dist-info/metadata.json
rdbms_subsetter-0.2.6.dist-info/top_level.txt
