Metadata-Version: 2.0
Name: rdbms-subsetter
Version: 0.2.6
Summary: Generate consistent subset of an RDBMS
Home-page: https://github.com/18F/rdbms-subsetter
Author: Catherine Devlin
Author-email: catherine.devlin@gsa.gov
License: CC0
Keywords: database testing
Platform: UNKNOWN
Classifier: Development Status :: 3 - Alpha
Classifier: License :: CC0 1.0 Universal (CC0 1.0) Public Domain Dedication
Classifier: Natural Language :: English
Classifier: Programming Language :: Python :: 2
Classifier: Programming Language :: Python :: 2.7
Classifier: Programming Language :: Python :: 3
Classifier: Programming Language :: Python :: 3.4
Classifier: Topic :: Database
Classifier: Topic :: Software Development :: Testing
Requires-Dist: blinker
Requires-Dist: sqlalchemy
